{
  "Order": {
    "Namespace": "Protechnic.Orders.Data.#",
    "Name": "Order",
    "Code": {
      "Version": "1.1.0",
      "Asymmetric": true,
      "Remarks": [
        "Interface implements IDated",
        "Poco implements IAccountableOrder",
        "Poco has additional methods",
        "Poco properties OrderStatus and Version have initial values",
        "Efco has additional methods"
      ]
    },
    "Abstract": "E,P",
    "Keys": [
      {
        "Type": "long"
      }
    ],
    "Properties": [
      {
        "Name": "Company",
        "Type": "string",
        "Comment": "E.g. PRO or STU",
        "Width": 3
      },
      {
        "Name": "Date",
        "Type": "DateTime",
        "Width": 20
      },
      {
        "Name": "Status",
        "Type": "OrderStatus",
        "Width": 3
      },
      {
        "Name": "Version",
        "Type": "string",
        "Column": "NotMapped",
        "Width": 5
      },
      {
        "Name": "Remark",
        "Type": "string?",
        "Width": 20
      }
    ],
    "Relations1toN": [
      {
        "Name": "Positions",
        "Type": "PositionM_E"
      },
      {
        "Name": "Payments",
        "Type": "PaymentM_E"
      },
      {
        "Name": "Shipments",
        "Type": "ShipmentM_E"
      }
    ],
    "RelationsMto1": [
      {
        "Name": "Contact",
        "Type": "ContactM_E?"
      }
    ]
  },
  "OrderPu": {
    "Namespace": "Protechnic.Orders.Data.#",
    "Name": "OrderPu",
    "Code": {
      "Version": "1.1.0",
      "Asymmetric": true,
      "ImportJsonFrom": "Order",
      "Remarks": [
        "Poco inherits from OrderMPE",
        "Efco inherits from OrderMEE",
        "Joiner uses Status.Abbr"
      ]
    },
    "Properties": [
      {
        "Name": "Supplier",
        "Type": "string",
        "Comment": "E.g. AMA, MIC, MIG, RIC",
        "Width": 3
      }
    ]
  },
  "OrderSa": {
    "Namespace": "Protechnic.Orders.Data.#",
    "Name": "OrderSa",
    "Code": {
      "Version": "1.1.0",
      "Asymmetric": true,
      "ImportJsonFrom": "Order",
      "Remarks": [
        "Poco inherits from OrderMPE",
        "Efco inherits from OrderMEE",
        "Poco implements IAddressableOrder",
        "Joiner uses Status.Abbr"
      ]
    },
    "Properties": [
      {
        "Name": "Channel",
        "Type": "string",
        "Comment": "E.g. ANO, BRI, PRO, RIC or LOA for a loan",
        "Width": 3
      }
    ],
    "Relations1to1": [
      {
        "Name": "Feedback",
        "Type": "FeedbackM_E?"
      },
      {
        "Name": "Voucher",
        "Type": "VoucherM_E?"
      }
    ]
  }
}
